picosdk/PicoDeviceEnums.py
picosdk/PicoDeviceStructs.py
picosdk/__init__.py
picosdk/constants.py
picosdk/ctypes_wrapper.py
picosdk/device.py
picosdk/discover.py
picosdk/errors.py
picosdk/functions.py
picosdk/library.py
picosdk/picohrdl.py
picosdk/pl1000.py
picosdk/ps2000.py
picosdk/ps2000a.py
picosdk/ps3000.py
picosdk/ps3000a.py
picosdk/ps4000.py
picosdk/ps4000a.py
picosdk/ps5000.py
picosdk/ps5000a.py
picosdk/ps6000.py
picosdk/ps6000a.py
picosdk/usbDrDaq.py
picosdk/usbPT104.py
picosdk/usbtc08.py
picosdk-1.0.dist-info/LICENSE.md
picosdk-1.0.dist-info/METADATA
picosdk-1.0.dist-info/WHEEL
picosdk-1.0.dist-info/top_level.txt
picosdk-1.0.dist-info/RECORD
